README.rst
setup.py
src/python/__init__.py
src/python/Cache/CacheManager.py
src/python/Cache/DataCacheLoader.py
src/python/Cache/DocumentCache.py
src/python/Cache/__init__.py
src/python/Databases/__init__.py
src/python/Databases/Mongo/MongoClient.py
src/python/Databases/Mongo/__init__.py
src/python/Databases/Oracle/OracleClient.py
src/python/Databases/Oracle/OracleDB.py
src/python/Databases/Oracle/__init__.py
src/python/MongoControllers/AgentController.py
src/python/MongoControllers/AssistanceController.py
src/python/MongoControllers/BatchController.py
src/python/MongoControllers/CampaignController.py
src/python/MongoControllers/CloseoutController.py
src/python/MongoControllers/ForceCompletionController.py
src/python/MongoControllers/ModuleLockController.py
src/python/MongoControllers/RMController.py
src/python/MongoControllers/RemainingDatasetController.py
src/python/MongoControllers/StartStopTimeController.py
src/python/MongoControllers/StatusHistoryController.py
src/python/MongoControllers/WTCController.py
src/python/MongoControllers/__init__.py
src/python/Services/ServicesChecker.py
src/python/Services/__init__.py
src/python/Services/ACDC/ACDCReader.py
src/python/Services/ACDC/__init__.py
src/python/Services/CRIC/CRICReader.py
src/python/Services/CRIC/__init__.py
src/python/Services/DBS/DBSReader.py
src/python/Services/DBS/DBSWriter.py
src/python/Services/DBS/__init__.py
src/python/Services/EOS/EOSReader.py
src/python/Services/EOS/EOSWriter.py
src/python/Services/EOS/__init__.py
src/python/Services/GWMSMon/GWMSMonReader.py
src/python/Services/GWMSMon/__init__.py
src/python/Services/Jira/JiraReader.py
src/python/Services/Jira/__init__.py
src/python/Services/MONIT/MONITReader.py
src/python/Services/MONIT/__init__.py
src/python/Services/McM/McMClient.py
src/python/Services/McM/__init__.py
src/python/Services/ReqMgr/ReqMgrReader.py
src/python/Services/ReqMgr/ReqMgrWriter.py
src/python/Services/ReqMgr/__init__.py
src/python/Services/Rucio/RucioReader.py
src/wmagentscripts.egg-info/PKG-INFO
src/wmagentscripts.egg-info/SOURCES.txt
src/wmagentscripts.egg-info/dependency_links.txt
src/wmagentscripts.egg-info/requires.txt
src/wmagentscripts.egg-info/top_level.txt