Metadata-Version: 1.2
Name: wmagentscripts
Version: 0.0.3
Summary: WMAgentScripts
Home-page: UNKNOWN
Author: Hasan Ozturk
License: UNKNOWN
Platform: UNKNOWN
Requires-Python: >=3.6
